memorystack/__init__.py
memorystack/client.py
memorystack/errors.py
memorystack/exceptions.py
memorystack/types.py
memorystack/integrations/__init__.py
memorystack/integrations/bedrock.py
memorystack/integrations/crewai.py
memorystack/integrations/gemini.py
memorystack/integrations/langchain.py
memorystack/integrations/langgraph.py
memorystack/integrations/llamaindex.py
memorystack/integrations/openai_helper.py
memorystack-1.0.4.dist-info/METADATA
memorystack-1.0.4.dist-info/WHEEL
memorystack-1.0.4.dist-info/top_level.txt
memorystack-1.0.4.dist-info/RECORD
