Metadata-Version: 2.4
Name: memorystack
Version: 1.0.4
Summary: Official Python SDK for MemoryStack - Semantic memory management for AI agents
Home-page: https://github.com/memorystack-labs/memorystack-python
Author: MemoryStack Team
Author-email: MemoryStack Team <support@memorystack.app>
License: MIT
Project-URL: Homepage, https://memorystack.app
Project-URL: Documentation, https://memorystack.app/docs
Project-URL: Repository, https://github.com/memorystack-labs/memorystack-python
Project-URL: Bug Reports, https://github.com/memorystack-labs/memorystack-python/issues
Keywords: ai,memory,semantic-search,agents,llm,machine-learning,memorystack
Classifier: Development Status :: 4 - Beta
Classifier: Intended Audience :: Developers
Classifier: Topic :: Software Development :: Libraries :: Python Modules
Classifier: Topic :: Scientific/Engineering :: Artificial Intelligence
Classifier: License :: OSI Approved :: MIT License
Classifier: Programming Language :: Python :: 3
Classifier: Programming Language :: Python :: 3.8
Classifier: Programming Language :: Python :: 3.9
Classifier: Programming Language :: Python :: 3.10
Classifier: Programming Language :: Python :: 3.11
Classifier: Programming Language :: Python :: 3.12
Requires-Python: >=3.8
Requires-Dist: requests>=2.31.0
Provides-Extra: dev
Requires-Dist: pytest>=7.0.0; extra == "dev"
Requires-Dist: pytest-cov>=4.0.0; extra == "dev"
Requires-Dist: black>=23.0.0; extra == "dev"
Requires-Dist: flake8>=6.0.0; extra == "dev"
Requires-Dist: mypy>=1.0.0; extra == "dev"
Requires-Dist: python-dotenv>=1.0.0; extra == "dev"
Provides-Extra: examples
Requires-Dist: python-dotenv>=1.0.0; extra == "examples"
Requires-Dist: google-generativeai>=0.3.0; extra == "examples"
Requires-Dist: crewai>=0.1.0; extra == "examples"
Requires-Dist: langchain>=0.1.0; extra == "examples"
Dynamic: author
Dynamic: home-page
Dynamic: requires-python
